[
  {
    "title": "Продам пів будинку",
    "url": "https://m.olx.ua/d/uk/obyavlenie/prodam-pv-budinku-ID10wmpt.html?search_reason=search%7Corganic",
    "search_name": "Продаж будинків",
    "area": 47.0,
    "price": 17500,
    "description": "Продам пів будинку: 17 500 $ - Продаж будинків Малин на Olx Перейти до основного вмісту Перейти до нижнього колонтитула Чат Укр Рус Повідомлення Повідомлення Ваш профіль Додати оголошення Пошук Назад Головна Нерухомість Будинки Продаж будинків Продаж будинків - Житомирська область Продаж будинків - Малин Рекламувати Підняти Бізнес Відстань до найближчого міста: У місті Поверховість: 1 Загальна площа: 47 м² Кількість кімнат: 2 Площа ділянки: 10 соток Тип будинку: Частина будинку Рік побудови / здачі: 1980 - 1989 Тип стін: Дерев'яний Тип покрівлі: Шифер Cанвузол: Роздільний Опалення: Індивідуальне газове Ремонт: Житловий стан Меблювання: Ні Мультимедіа: Wi-Fi Комфорт: Цоколь, підвал, Огорожа, Сад, город, Душова кабіна Комунікації: Асфальтована дорога, Електрика, Газ, Каналізація септик, Центральний водопровід Інфраструктура (до 500 метрів): Відділення банку, банкомат, Центр міста, Ринок, Парк, зелена зона, Відділення пошти, Школа, Магазин, кіоск, Супермаркет, ТРЦ, Зупинка транспорту Ланд",
    "city": "Малин",
    "active": true,
    "found_at": "2026-06-07 16:25:24"
  }
]